gogokit/__init__.py
gogokit/clients.py
gogokit/config.py
gogokit/exceptions.py
gogokit/hal.py
gogokit/http_client.py
gogokit/oauth.py
gogokit/resources.py
gogokit-0.2.0.dist-info/METADATA
gogokit-0.2.0.dist-info/RECORD
gogokit-0.2.0.dist-info/WHEEL
gogokit-0.2.0.dist-info/top_level.txt
