Metadata-Version: 2.1
Name: gogokit
Version: 0.2.0
Summary: GogoKit is a lightweight, viagogo API client library for Python.
Home-page: https://github.com/viagogo/gogokit.py
Author: Viagogo
Author-email: api@viagogo.com
License: Copyright (c) 2020 viagogo
Requires-Dist: requests (>=2.7.0)
Requires-Dist: uritemplate (>=0.6)
Requires-Dist: iso8601 (>=0.1.10)
Requires-Dist: six (>=1.9.0)
